ColemenLogger.py
Colors.py
LoadingBar.py
SingleLine.py
colemenLogger-0.1.4.dist-info/METADATA
colemenLogger-0.1.4.dist-info/WHEEL
colemenLogger-0.1.4.dist-info/top_level.txt
colemenLogger-0.1.4.dist-info/RECORD
